{
  "version": "7",
  "dialect": "postgresql",
  "entries": [
    {
      "idx": 0,
      "version": "7",
      "when": 1738338195392,
      "tag": "0000_certain_moonstone",
      "breakpoints": true
    },
    {
      "idx": 1,
      "version": "7",
      "when": 1738437510666,
      "tag": "0001_windy_smiling_tiger",
      "breakpoints": true
    },
    {
      "idx": 2,
      "version": "7",
      "when": 1738787664766,
      "tag": "0002_last_pandemic",
      "breakpoints": true
    },
    {
      "idx": 3,
      "version": "7",
      "when": 1738794006644,
      "tag": "0003_unique_meggan",
      "breakpoints": true
    },
    {
      "idx": 4,
      "version": "7",
      "when": 1738796023706,
      "tag": "0004_orange_ezekiel_stane",
      "breakpoints": true
    },
    {
      "idx": 5,
      "version": "7",
      "when": 1738796376495,
      "tag": "0005_complex_cammi",
      "breakpoints": true
    }
  ]
}